case_insensitive_string_set/__init__.py
case_insensitive_string_set/_ci_str_set.py
case_insensitive_string_set/py.typed
case_insensitive_string_set/version.py
case_insensitive_string_set-1.0.0.dist-info/licenses/LICENSE
case_insensitive_string_set-1.0.0.dist-info/METADATA
case_insensitive_string_set-1.0.0.dist-info/WHEEL
case_insensitive_string_set-1.0.0.dist-info/top_level.txt
case_insensitive_string_set-1.0.0.dist-info/RECORD
