Metadata-Version: 2.4
Name: case_insensitive_string_set
Version: 1.0.0
Summary: A set class for case-insensitive strings.
Author-email: Rudolf Byker <rudolfbyker@gmail.com>
Project-URL: repository, https://github.com/rudolfbyker/case_insensitive_string_set
Classifier: Programming Language :: Python :: 3
Classifier: License :: Other/Proprietary License
Classifier: Operating System :: OS Independent
Requires-Python: >=3.8
License-File: LICENSE
Dynamic: license-file
